{
  "image_id": "crazing_92.jpg",
  "lighting_condition": "low_light",
  "defects": [
    {
      "defect_type": "Crazing",
      "location": [
        0.445,
        0.3239,
        0.8379,
        0.368
      ],
      "confidence_score": 0.95,
      "severity": "Medium",
      "visual_analysis": "该区域存在明显的裂纹状缺陷，表现为细小的裂缝和不规则的纹理。",
      "suggestion": "建议对该区域进行局部打磨处理，并重新喷涂以修复裂纹。"
    },
    {
      "defect_type": "Crazing",
      "location": [
        0.4659,
        0.7382,
        0.9252,
        0.4564
      ],
      "confidence_score": 0.9,
      "severity": "Medium",
      "visual_analysis": "该区域也存在裂纹状缺陷，表现为细小的裂缝和不规则的纹理。",
      "suggestion": "建议对该区域进行局部打磨处理，并重新喷涂以修复裂纹。"
    },
    {
      "defect_type": "Pitted Surface",
      "location": [
        0.2,
        0.2,
        0.6,
        0.6
      ],
      "confidence_score": 0.85,
      "severity": "Low",
      "visual_analysis": "该区域存在轻微的点蚀现象，表现为表面的小坑洞。",
      "suggestion": "建议对该区域进行局部打磨处理，但无需特别处理。"
    }
  ]
}