{
  "image_id": "rolled-in_scale_156.jpg",
  "lighting_condition": "low_light",
  "defects": [
    {
      "defect_type": "Rolled-in Scale",
      "location": [
        0.1835,
        0.5321,
        0.2727,
        0.7572
      ],
      "confidence_score": 1.0,
      "severity": "Medium",
      "visual_analysis": "该区域存在明显的氧化皮压入现象，表现为不规则的凸起和凹陷。",
      "suggestion": "建议对该区域进行打磨处理，以去除氧化皮并恢复钢材表面平整度。"
    },
    {
      "defect_type": "Rolled-in Scale",
      "location": [
        0.6116,
        0.5869,
        0.2256,
        0.26
      ],
      "confidence_score": 1.0,
      "severity": "Low",
      "visual_analysis": "该区域的氧化皮压入现象较为轻微，但仍有明显痕迹。",
      "suggestion": "建议对该区域进行局部打磨，以改善外观质量。"
    },
    {
      "defect_type": "Pitted Surface",
      "location": [
        0.4,
        0.3,
        0.6,
        0.4
      ],
      "confidence_score": 0.8,
      "severity": "Low",
      "visual_analysis": "该区域存在点蚀现象，表现为小范围的凹坑状缺陷。",
      "suggestion": "建议对该区域进行局部修复，以防止进一步腐蚀。"
    }
  ]
}