{
  "image_id": "scratches_161.jpg",
  "lighting_condition": "low_light",
  "defects": [
    {
      "defect_type": "Scratches",
      "location": [
        0.257949,
        0.309251,
        0.061968,
        0.654285
      ],
      "confidence_score": 0.95,
      "severity": "Medium",
      "visual_analysis": "该区域存在明显的条状痕迹，类似于划痕，与背景纹理明显不同。",
      "suggestion": "建议对该区域进行打磨处理，以去除划痕并恢复表面光滑度。"
    },
    {
      "defect_type": "Scratches",
      "location": [
        0.71401,
        0.536568,
        0.122962,
        0.904243
      ],
      "confidence_score": 0.9,
      "severity": "Low",
      "visual_analysis": "该区域的条状痕迹较为细小，且与背景纹理相似，可能存在误判。建议进一步检查确认。",
      "suggestion": "建议对该区域进行局部检查，确认是否存在实际划痕。"
    }
  ],
  "overall_assessment": {
    "defect_count": 2,
    "risk_level": "Medium"
  }
}