{
  "image_id": "crazing_272.jpg",
  "lighting_condition": "low_light",
  "defects": [
    {
      "defect_type": "Crazing",
      "location": [
        0.320672,
        0.466134,
        0.577561,
        0.360727
      ],
      "confidence_score": 0.44,
      "severity": "High",
      "visual_analysis": "图像中存在明显的裂纹特征，覆盖了较大区域。",
      "suggestion": "立即修复，优先处理。"
    },
    {
      "defect_type": "Crazing",
      "location": [
        0.593357,
        0.183479,
        0.739022,
        0.34192
      ],
      "confidence_score": 0.27,
      "severity": "High",
      "visual_analysis": "图像中存在明显的裂纹特征，覆盖了较大区域。",
      "suggestion": "立即修复，优先处理。"
    },
    {
      "defect_type": "Crazing",
      "location": [
        0.471025,
        0.766126,
        0.953369,
        0.364977
      ],
      "confidence_score": 0.79,
      "severity": "High",
      "visual_analysis": "图像中存在明显的裂纹特征，覆盖了较大区域。",
      "suggestion": "立即修复，优先处理。"
    }
  ],
  "overall_assessment": {
    "defect_count": 3,
    "risk_level": "High"
  }
}