{
  "image_id": "rolled-in_scale_300.jpg",
  "lighting_condition": "low_light",
  "defects": [
    {
      "defect_type": "Rolled-in Scale",
      "location": [
        0.42997,
        0.795887,
        0.332684,
        0.380649
      ],
      "confidence_score": 0.21,
      "severity": "Medium",
      "visual_analysis": "图像中存在明显的Rolled-in Scale特征，面积占比为0.1266。",
      "suggestion": "建议人工复核以确认是否需要修复。"
    },
    {
      "defect_type": "Rolled-in Scale",
      "location": [
        0.405875,
        0.233246,
        0.255407,
        0.302768
      ],
      "confidence_score": 0.42,
      "severity": "Medium",
      "visual_analysis": "图像中存在明显的Rolled-in Scale特征，面积占比为0.0773。",
      "suggestion": "建议人工复核以确认是否需要修复。"
    }
  ],
  "overall_assessment": {
    "defect_count": 2,
    "risk_level": "High"
  }
}