{
  "image_id": "scratches_283.jpg",
  "lighting_condition": "low_light",
  "defects": [
    {
      "defect_type": "Scratches",
      "location": [
        0.422263,
        0.71203,
        0.838174,
        0.15388
      ],
      "confidence_score": 0.8,
      "severity": "Medium",
      "visual_analysis": "图像中存在明显的刮痕，面积占比约为12.9%，在低光照条件下特征较为突出。",
      "suggestion": "建议人工复核以确认是否需要修复。"
    },
    {
      "defect_type": "Scratches",
      "location": [
        0.52112,
        0.096754,
        0.881285,
        0.158503
      ],
      "confidence_score": 0.71,
      "severity": "Medium",
      "visual_analysis": "图像中存在明显的刮痕，面积占比约为13.97%，在低光照条件下特征较为突出。",
      "suggestion": "建议人工复核以确认是否需要修复。"
    }
  ],
  "overall_assessment": {
    "defect_count": 2,
    "risk_level": "High"
  }
}