{
  "image_id": "patches_72.jpg",
  "lighting_condition": "low_light",
  "defects": [
    {
      "defect_type": "Patches",
      "location": [
        0.145583,
        0.386581,
        0.207106,
        0.243648
      ],
      "confidence_score": 0.9,
      "severity": "High",
      "visual_analysis": "图像中存在明显的黑色斑块，可能影响产品的外观和功能。",
      "suggestion": "建议立即更换或修复该区域，以确保产品质量符合标准。"
    },
    {
      "defect_type": "Patches",
      "location": [
        0.838692,
        0.400595,
        0.158669,
        0.31026
      ],
      "confidence_score": 0.82,
      "severity": "High",
      "visual_analysis": "图像中存在明显的黑色斑块，可能影响产品的外观和功能。",
      "suggestion": "建议立即更换或修复该区域，以确保产品质量符合标准。"
    }
  ],
  "overall_assessment": {
    "defect_count": 2,
    "risk_level": "High"
  }
}