{
  "image_id": "scratches_221.jpg",
  "lighting_condition": "low_light",
  "defects": [
    {
      "defect_type": "Scratches",
      "location": [
        0.173256,
        0.39958,
        0.1201,
        0.687725
      ],
      "confidence_score": 0.66,
      "severity": "High",
      "visual_analysis": "图像中存在明显的划痕，影响表面光滑度。",
      "suggestion": "建议立即更换或修复受影响区域，以确保产品质量和安全。"
    },
    {
      "defect_type": "Scratches",
      "location": [
        0.846096,
        0.556428,
        0.111991,
        0.715734
      ],
      "confidence_score": 0.66,
      "severity": "High",
      "visual_analysis": "图像中存在明显的划痕，影响表面光滑度。",
      "suggestion": "建议立即更换或修复受影响区域，以确保产品质量和安全。"
    },
    {
      "defect_type": "Scratches",
      "location": [
        0.472732,
        0.381067,
        0.111635,
        0.74128
      ],
      "confidence_score": 0.64,
      "severity": "High",
      "visual_analysis": "图像中存在明显的划痕，影响表面光滑度。",
      "suggestion": "建议立即更换或修复受影响区域，以确保产品质量和安全。"
    }
  ],
  "overall_assessment": {
    "defect_count": 3,
    "risk_level": "High"
  }
}