{
  "image_id": "scratches_87.jpg",
  "lighting_condition": "low_light",
  "defects": [
    {
      "defect_type": "Scratches",
      "location": [
        0.748361,
        0.491126,
        0.036146,
        0.929043
      ],
      "confidence_score": 0.68,
      "severity": "High",
      "visual_analysis": "图像中存在明显的划痕，覆盖了大面积区域，影响产品的外观和使用体验。",
      "suggestion": "建议立即更换或修复该部件，并在后续生产过程中加强质量控制，确保此类缺陷不再发生。"
    }
  ],
  "overall_assessment": {
    "defect_count": 1,
    "risk_level": "High"
  }
}